EvoScientist/EvoScientist.py
EvoScientist/__init__.py
EvoScientist/__main__.py
EvoScientist/backends.py
EvoScientist/cli.py
EvoScientist/middleware.py
EvoScientist/prompts.py
EvoScientist/subagent.yaml
EvoScientist/tools.py
EvoScientist/utils.py
EvoScientist/stream/__init__.py
EvoScientist/stream/emitter.py
EvoScientist/stream/formatter.py
EvoScientist/stream/tracker.py
EvoScientist/stream/utils.py
evoscientist-0.1.0rc1.dist-info/licenses/LICENSE
evoscientist-0.1.0rc1.dist-info/METADATA
evoscientist-0.1.0rc1.dist-info/WHEEL
evoscientist-0.1.0rc1.dist-info/entry_points.txt
evoscientist-0.1.0rc1.dist-info/top_level.txt
evoscientist-0.1.0rc1.dist-info/RECORD
