Metadata-Version: 2.4
Name: EvoScientist
Version: 0.1.0rc1
Summary: EvoScientist: Towards Self-Evolving AI Scientists for End-to-End Scientific Discovery
Author: Xi Zhang
Maintainer: Xi Zhang
License-Expression: MIT
Project-URL: Homepage, https://github.com/EvoScientist/EvoScientist
Project-URL: Bug Tracker, https://github.com/EvoScientist/EvoScientist/issues
Project-URL: Documentation, https://github.com/EvoScientist/EvoScientist#readme
Keywords: ai-scientific,scientific-discovery,self-evolving,ai-scientists,end-to-end
Classifier: Programming Language :: Python :: 3
Requires-Python: >=3.11
License-File: LICENSE
Requires-Dist: deepagents>=0.3.6
Requires-Dist: langchain>=1.2
Requires-Dist: langchain-anthropic>=1.3
Requires-Dist: anthropic>=0.76
Requires-Dist: tavily-python>=0.7
Requires-Dist: pyyaml>=6.0
Requires-Dist: rich>=14.0
Requires-Dist: prompt-toolkit>=3.0
Requires-Dist: python-dotenv>=1.0
Requires-Dist: langgraph-cli[inmem]>=0.4
Requires-Dist: httpx>=0.27
Requires-Dist: markdownify>=0.14
Provides-Extra: dev
Requires-Dist: pytest>=8.0; extra == "dev"
Requires-Dist: pytest-cov>=5.0; extra == "dev"
Dynamic: license-file
